{
  "fio version" : "fio-3.28",
  "timestamp" : 1743416390,
  "timestamp_ms" : 1743416390456,
  "time" : "Mon Mar 31 19:19:50 2025",
  "global options" : {
    "bs" : "256k",
    "ioengine" : "io_uring",
    "size" : "12G",
    "numjobs" : "4",
    "iodepth" : "16",
    "group_reporting" : "1",
    "direct" : "1",
    "thread" : "1",
    "filename" : "/dev/nvme3n1"
  },
  "jobs" : [
    {
      "jobname" : "randwrite",
      "groupid" : 0,
      "error" : 0,
      "eta" : 0,
      "elapsed" : 17,
      "job options" : {
        "rw" : "randrw"
      },
      "read" : {
        "io_bytes" : 25718161408,
        "io_kbytes" : 25115392,
        "bw_bytes" : 1591174992,
        "bw" : 1553881,
        "iops" : 6069.850894,
        "runtime" : 16163,
        "total_ios" : 98107,
        "short_ios" : 0,
        "drop_ios" : 0,
        "slat_ns" : {
          "min" : 6800,
          "max" : 228507,
          "mean" : 10622.673775,
          "stddev" : 1855.160244,
          "N" : 98107
        },
        "clat_ns" : {
          "min" : 16570,
          "max" : 50173210,
          "mean" : 9801884.228363,
          "stddev" : 9377381.182659,
          "N" : 98107,
          "percentile" : {
            "1.000000" : 26752,
            "5.000000" : 31872,
            "10.000000" : 36096,
            "20.000000" : 46336,
            "30.000000" : 63744,
            "40.000000" : 1908736,
            "50.000000" : 12910592,
            "60.000000" : 13959168,
            "70.000000" : 15138816,
            "80.000000" : 16449536,
            "90.000000" : 19529728,
            "95.000000" : 23986176,
            "99.000000" : 39059456,
            "99.500000" : 43253760,
            "99.900000" : 47972352,
            "99.950000" : 48496640,
            "99.990000" : 49545216
          }
        },
        "lat_ns" : {
          "min" : 26490,
          "max" : 50181310,
          "mean" : 9812577.760822,
          "stddev" : 9377409.887419,
          "N" : 98107
        },
        "bw_min" : 1312256,
        "bw_max" : 2234996,
        "bw_agg" : 100.000000,
        "bw_mean" : 1556307.625000,
        "bw_dev" : 55319.938259,
        "bw_samples" : 128,
        "iops_min" : 5126,
        "iops_max" : 8730,
        "iops_mean" : 6079.312500,
        "iops_stddev" : 216.081803,
        "iops_samples" : 128
      },
      "write" : {
        "io_bytes" : 25821446144,
        "io_kbytes" : 25216256,
        "bw_bytes" : 1597565188,
        "bw" : 1560122,
        "iops" : 6094.227557,
        "runtime" : 16163,
        "total_ios" : 98501,
        "short_ios" : 0,
        "drop_ios" : 0,
        "slat_ns" : {
          "min" : 8050,
          "max" : 43349,
          "mean" : 13684.876499,
          "stddev" : 1970.143369,
          "N" : 98501
        },
        "clat_ns" : {
          "min" : 101489,
          "max" : 9873267,
          "mean" : 675812.175156,
          "stddev" : 816818.046922,
          "N" : 98501,
          "percentile" : {
            "1.000000" : 120320,
            "5.000000" : 130560,
            "10.000000" : 154624,
            "20.000000" : 203776,
            "30.000000" : 252928,
            "40.000000" : 325632,
            "50.000000" : 411648,
            "60.000000" : 528384,
            "70.000000" : 675840,
            "80.000000" : 913408,
            "90.000000" : 1368064,
            "95.000000" : 2072576,
            "99.000000" : 4620288,
            "99.500000" : 4882432,
            "99.900000" : 6520832,
            "99.950000" : 7110656,
            "99.990000" : 8716288
          }
        },
        "lat_ns" : {
          "min" : 125539,
          "max" : 9886257,
          "mean" : 689568.535325,
          "stddev" : 816937.228145,
          "N" : 98501
        },
        "bw_min" : 1255936,
        "bw_max" : 2353813,
        "bw_agg" : 100.000000,
        "bw_mean" : 1564132.656250,
        "bw_dev" : 62091.620483,
        "bw_samples" : 128,
        "iops_min" : 4906,
        "iops_max" : 9194,
        "iops_mean" : 6109.875000,
        "iops_stddev" : 242.531328,
        "iops_samples" : 128
      },
      "trim" : {
        "io_bytes" : 0,
        "io_kbytes" : 0,
        "bw_bytes" : 0,
        "bw" : 0,
        "iops" : 0.000000,
        "runtime" : 0,
        "total_ios" : 0,
        "short_ios" : 0,
        "drop_ios" : 0,
        "slat_ns" : {
          "min" : 0,
          "max" : 0,
          "mean" : 0.000000,
          "stddev" : 0.000000,
          "N" : 0
        },
        "clat_ns" : {
          "min" : 0,
          "max" : 0,
          "mean" : 0.000000,
          "stddev" : 0.000000,
          "N" : 0
        },
        "lat_ns" : {
          "min" : 0,
          "max" : 0,
          "mean" : 0.000000,
          "stddev" : 0.000000,
          "N" : 0
        },
        "bw_min" : 0,
        "bw_max" : 0,
        "bw_agg" : 0.000000,
        "bw_mean" : 0.000000,
        "bw_dev" : 0.000000,
        "bw_samples" : 0,
        "iops_min" : 0,
        "iops_max" : 0,
        "iops_mean" : 0.000000,
        "iops_stddev" : 0.000000,
        "iops_samples" : 0
      },
      "sync" : {
        "total_ios" : 0,
        "lat_ns" : {
          "min" : 0,
          "max" : 0,
          "mean" : 0.000000,
          "stddev" : 0.000000,
          "N" : 0
        }
      },
      "job_runtime" : 64418,
      "usr_cpu" : 0.574374,
      "sys_cpu" : 5.059145,
      "ctx" : 184924,
      "majf" : 0,
      "minf" : 0,
      "iodepth_level" : {
        "1" : 0.100000,
        "2" : 0.100000,
        "4" : 0.100000,
        "8" : 0.100000,
        "16" : 99.969482,
        "32" : 0.000000,
        ">=64" : 0.000000
      },
      "iodepth_submit" : {
        "0" : 0.000000,
        "4" : 100.000000,
        "8" : 0.000000,
        "16" : 0.000000,
        "32" : 0.000000,
        "64" : 0.000000,
        ">=64" : 0.000000
      },
      "iodepth_complete" : {
        "0" : 0.000000,
        "4" : 99.997965,
        "8" : 0.000000,
        "16" : 0.100000,
        "32" : 0.000000,
        "64" : 0.000000,
        ">=64" : 0.000000
      },
      "latency_ns" : {
        "2" : 0.000000,
        "4" : 0.000000,
        "10" : 0.000000,
        "20" : 0.000000,
        "50" : 0.000000,
        "100" : 0.000000,
        "250" : 0.000000,
        "500" : 0.000000,
        "750" : 0.000000,
        "1000" : 0.000000
      },
      "latency_us" : {
        "2" : 0.000000,
        "4" : 0.000000,
        "10" : 0.000000,
        "20" : 0.010000,
        "50" : 11.564636,
        "100" : 6.022135,
        "250" : 15.623474,
        "500" : 14.442952,
        "750" : 8.201599,
        "1000" : 4.863485
      },
      "latency_ms" : {
        "2" : 6.776937,
        "4" : 3.020732,
        "10" : 1.372782,
        "20" : 23.625692,
        "50" : 4.479472,
        "100" : 0.010000,
        "250" : 0.000000,
        "500" : 0.000000,
        "750" : 0.000000,
        "1000" : 0.000000,
        "2000" : 0.000000,
        ">=2000" : 0.000000
      },
      "latency_depth" : 16,
      "latency_target" : 0,
      "latency_percentile" : 100.000000,
      "latency_window" : 0
    }
  ],
  "disk_util" : [
    {
      "name" : "nvme3n1",
      "read_ios" : 98167,
      "write_ios" : 98425,
      "read_merges" : 0,
      "write_merges" : 0,
      "read_ticks" : 960790,
      "write_ticks" : 66144,
      "in_queue" : 1026935,
      "util" : 99.402783
    }
  ]
}
