{
  "fio version" : "fio-3.28",
  "timestamp" : 1743447965,
  "timestamp_ms" : 1743447965329,
  "time" : "Tue Apr  1 04:06:05 2025",
  "global options" : {
    "bs" : "16k",
    "ioengine" : "io_uring",
    "size" : "12G",
    "numjobs" : "4",
    "iodepth" : "16",
    "group_reporting" : "1",
    "direct" : "1",
    "thread" : "1",
    "filename" : "/dev/nvme3n1"
  },
  "jobs" : [
    {
      "jobname" : "seqwrite",
      "groupid" : 0,
      "error" : 0,
      "eta" : 0,
      "elapsed" : 18,
      "job options" : {
        "rw" : "rw"
      },
      "read" : {
        "io_bytes" : 25767870464,
        "io_kbytes" : 25163936,
        "bw_bytes" : 1459357221,
        "bw" : 1425153,
        "iops" : 89072.096053,
        "runtime" : 17657,
        "total_ios" : 1572746,
        "short_ios" : 0,
        "drop_ios" : 0,
        "slat_ns" : {
          "min" : 1780,
          "max" : 119639,
          "mean" : 2344.057288,
          "stddev" : 706.755570,
          "N" : 1572746
        },
        "clat_ns" : {
          "min" : 3710,
          "max" : 14840132,
          "mean" : 581064.170368,
          "stddev" : 971260.314438,
          "N" : 1572746,
          "percentile" : {
            "1.000000" : 37120,
            "5.000000" : 46336,
            "10.000000" : 55552,
            "20.000000" : 94720,
            "30.000000" : 123392,
            "40.000000" : 166912,
            "50.000000" : 216064,
            "60.000000" : 268288,
            "70.000000" : 346112,
            "80.000000" : 733184,
            "90.000000" : 1843200,
            "95.000000" : 2473984,
            "99.000000" : 3227648,
            "99.500000" : 5734400,
            "99.900000" : 11206656,
            "99.950000" : 12255232,
            "99.990000" : 13697024
          }
        },
        "lat_ns" : {
          "min" : 5830,
          "max" : 14842701,
          "mean" : 583455.821154,
          "stddev" : 971283.237329,
          "N" : 1572746
        },
        "bw_min" : 436576,
        "bw_max" : 3448544,
        "bw_agg" : 100.000000,
        "bw_mean" : 1818861.885714,
        "bw_dev" : 237769.595008,
        "bw_samples" : 121,
        "iops_min" : 27286,
        "iops_max" : 215534,
        "iops_mean" : 113678.867857,
        "iops_stddev" : 14860.599688,
        "iops_samples" : 121
      },
      "write" : {
        "io_bytes" : 25771737088,
        "io_kbytes" : 25167712,
        "bw_bytes" : 1459576207,
        "bw" : 1425367,
        "iops" : 89085.461856,
        "runtime" : 17657,
        "total_ios" : 1572982,
        "short_ios" : 0,
        "drop_ios" : 0,
        "slat_ns" : {
          "min" : 1710,
          "max" : 135028,
          "mean" : 2568.905805,
          "stddev" : 794.923506,
          "N" : 1572982
        },
        "clat_ns" : {
          "min" : 350,
          "max" : 1062968,
          "mean" : 34299.906895,
          "stddev" : 17521.929311,
          "N" : 1572982,
          "percentile" : {
            "1.000000" : 14784,
            "5.000000" : 15680,
            "10.000000" : 16512,
            "20.000000" : 19072,
            "30.000000" : 21376,
            "40.000000" : 24448,
            "50.000000" : 28544,
            "60.000000" : 33536,
            "70.000000" : 41216,
            "80.000000" : 50944,
            "90.000000" : 61184,
            "95.000000" : 68096,
            "99.000000" : 81408,
            "99.500000" : 86528,
            "99.900000" : 97792,
            "99.950000" : 102912,
            "99.990000" : 119296
          }
        },
        "lat_ns" : {
          "min" : 14710,
          "max" : 1066248,
          "mean" : 36916.706459,
          "stddev" : 17561.455069,
          "N" : 1572982
        },
        "bw_min" : 432352,
        "bw_max" : 3453312,
        "bw_agg" : 100.000000,
        "bw_mean" : 1818298.742857,
        "bw_dev" : 237173.299409,
        "bw_samples" : 121,
        "iops_min" : 27022,
        "iops_max" : 215832,
        "iops_mean" : 113643.671429,
        "iops_stddev" : 14823.331213,
        "iops_samples" : 121
      },
      "trim" : {
        "io_bytes" : 0,
        "io_kbytes" : 0,
        "bw_bytes" : 0,
        "bw" : 0,
        "iops" : 0.000000,
        "runtime" : 0,
        "total_ios" : 0,
        "short_ios" : 0,
        "drop_ios" : 0,
        "slat_ns" : {
          "min" : 0,
          "max" : 0,
          "mean" : 0.000000,
          "stddev" : 0.000000,
          "N" : 0
        },
        "clat_ns" : {
          "min" : 0,
          "max" : 0,
          "mean" : 0.000000,
          "stddev" : 0.000000,
          "N" : 0
        },
        "lat_ns" : {
          "min" : 0,
          "max" : 0,
          "mean" : 0.000000,
          "stddev" : 0.000000,
          "N" : 0
        },
        "bw_min" : 0,
        "bw_max" : 0,
        "bw_agg" : 0.000000,
        "bw_mean" : 0.000000,
        "bw_dev" : 0.000000,
        "bw_samples" : 0,
        "iops_min" : 0,
        "iops_max" : 0,
        "iops_mean" : 0.000000,
        "iops_stddev" : 0.000000,
        "iops_samples" : 0
      },
      "sync" : {
        "total_ios" : 0,
        "lat_ns" : {
          "min" : 0,
          "max" : 0,
          "mean" : 0.000000,
          "stddev" : 0.000000,
          "N" : 0
        }
      },
      "job_runtime" : 61025,
      "usr_cpu" : 4.063908,
      "sys_cpu" : 20.412946,
      "ctx" : 2073763,
      "majf" : 0,
      "minf" : 0,
      "iodepth_level" : {
        "1" : 0.100000,
        "2" : 0.100000,
        "4" : 0.100000,
        "8" : 0.100000,
        "16" : 99.998093,
        "32" : 0.000000,
        ">=64" : 0.000000
      },
      "iodepth_submit" : {
        "0" : 0.000000,
        "4" : 100.000000,
        "8" : 0.000000,
        "16" : 0.000000,
        "32" : 0.000000,
        "64" : 0.000000,
        ">=64" : 0.000000
      },
      "iodepth_complete" : {
        "0" : 0.000000,
        "4" : 99.999873,
        "8" : 0.000000,
        "16" : 0.100000,
        "32" : 0.000000,
        "64" : 0.000000,
        ">=64" : 0.000000
      },
      "latency_ns" : {
        "2" : 0.000000,
        "4" : 0.000000,
        "10" : 0.000000,
        "20" : 0.000000,
        "50" : 0.000000,
        "100" : 0.000000,
        "250" : 0.000000,
        "500" : 0.010000,
        "750" : 0.000000,
        "1000" : 0.000000
      },
      "latency_us" : {
        "2" : 0.000000,
        "4" : 0.010000,
        "10" : 0.058683,
        "20" : 12.277540,
        "50" : 30.793603,
        "100" : 17.451954,
        "250" : 17.773406,
        "500" : 10.768382,
        "750" : 0.911395,
        "1000" : 0.542990
      },
      "latency_ms" : {
        "2" : 5.384922,
        "4" : 3.613408,
        "10" : 0.347106,
        "20" : 0.076199,
        "50" : 0.000000,
        "100" : 0.000000,
        "250" : 0.000000,
        "500" : 0.000000,
        "750" : 0.000000,
        "1000" : 0.000000,
        "2000" : 0.000000,
        ">=2000" : 0.000000
      },
      "latency_depth" : 16,
      "latency_target" : 0,
      "latency_percentile" : 100.000000,
      "latency_window" : 0
    }
  ],
  "disk_util" : [
    {
      "name" : "nvme3n1",
      "read_ios" : 1572139,
      "write_ios" : 1572182,
      "read_merges" : 0,
      "write_merges" : 0,
      "read_ticks" : 906662,
      "write_ticks" : 46740,
      "in_queue" : 953402,
      "util" : 99.464517
    }
  ]
}
