{
  "fio version" : "fio-3.28",
  "timestamp" : 1740557224,
  "timestamp_ms" : 1740557224724,
  "time" : "Wed Feb 26 17:07:04 2025",
  "global options" : {
    "bs" : "64k",
    "ioengine" : "io_uring",
    "size" : "12G",
    "numjobs" : "4",
    "iodepth" : "16",
    "group_reporting" : "1",
    "direct" : "1",
    "thread" : "1",
    "filename" : "/dev/nvme3n1"
  },
  "jobs" : [
    {
      "jobname" : "seqwrite",
      "groupid" : 0,
      "error" : 0,
      "eta" : 0,
      "elapsed" : 23,
      "job options" : {
        "rw" : "write"
      },
      "read" : {
        "io_bytes" : 0,
        "io_kbytes" : 0,
        "bw_bytes" : 0,
        "bw" : 0,
        "iops" : 0.000000,
        "runtime" : 0,
        "total_ios" : 0,
        "short_ios" : 0,
        "drop_ios" : 0,
        "slat_ns" : {
          "min" : 0,
          "max" : 0,
          "mean" : 0.000000,
          "stddev" : 0.000000,
          "N" : 0
        },
        "clat_ns" : {
          "min" : 0,
          "max" : 0,
          "mean" : 0.000000,
          "stddev" : 0.000000,
          "N" : 0
        },
        "lat_ns" : {
          "min" : 0,
          "max" : 0,
          "mean" : 0.000000,
          "stddev" : 0.000000,
          "N" : 0
        },
        "bw_min" : 0,
        "bw_max" : 0,
        "bw_agg" : 0.000000,
        "bw_mean" : 0.000000,
        "bw_dev" : 0.000000,
        "bw_samples" : 0,
        "iops_min" : 0,
        "iops_max" : 0,
        "iops_mean" : 0.000000,
        "iops_stddev" : 0.000000,
        "iops_samples" : 0
      },
      "write" : {
        "io_bytes" : 51539607552,
        "io_kbytes" : 50331648,
        "bw_bytes" : 2341432289,
        "bw" : 2286554,
        "iops" : 35727.421407,
        "runtime" : 22012,
        "total_ios" : 786432,
        "short_ios" : 0,
        "drop_ios" : 0,
        "slat_ns" : {
          "min" : 3060,
          "max" : 49699,
          "mean" : 5278.926365,
          "stddev" : 1092.291285,
          "N" : 786432
        },
        "clat_ns" : {
          "min" : 33520,
          "max" : 10623953,
          "mean" : 1782992.422263,
          "stddev" : 1066370.536573,
          "N" : 786432,
          "percentile" : {
            "1.000000" : 423936,
            "5.000000" : 518144,
            "10.000000" : 667648,
            "20.000000" : 888832,
            "30.000000" : 1105920,
            "40.000000" : 1335296,
            "50.000000" : 1548288,
            "60.000000" : 1794048,
            "70.000000" : 2146304,
            "80.000000" : 2539520,
            "90.000000" : 3194880,
            "95.000000" : 3817472,
            "99.000000" : 5275648,
            "99.500000" : 5799936,
            "99.900000" : 7241728,
            "99.950000" : 7700480,
            "99.990000" : 8716288
          }
        },
        "lat_ns" : {
          "min" : 43430,
          "max" : 10629693,
          "mean" : 1788331.490513,
          "stddev" : 1066350.942258,
          "N" : 786432
        },
        "bw_min" : 2022016,
        "bw_max" : 2636160,
        "bw_agg" : 100.000000,
        "bw_mean" : 2291520.541226,
        "bw_dev" : 33425.033184,
        "bw_samples" : 174,
        "iops_min" : 31594,
        "iops_max" : 41190,
        "iops_mean" : 35805.008457,
        "iops_stddev" : 522.266144,
        "iops_samples" : 174
      },
      "trim" : {
        "io_bytes" : 0,
        "io_kbytes" : 0,
        "bw_bytes" : 0,
        "bw" : 0,
        "iops" : 0.000000,
        "runtime" : 0,
        "total_ios" : 0,
        "short_ios" : 0,
        "drop_ios" : 0,
        "slat_ns" : {
          "min" : 0,
          "max" : 0,
          "mean" : 0.000000,
          "stddev" : 0.000000,
          "N" : 0
        },
        "clat_ns" : {
          "min" : 0,
          "max" : 0,
          "mean" : 0.000000,
          "stddev" : 0.000000,
          "N" : 0
        },
        "lat_ns" : {
          "min" : 0,
          "max" : 0,
          "mean" : 0.000000,
          "stddev" : 0.000000,
          "N" : 0
        },
        "bw_min" : 0,
        "bw_max" : 0,
        "bw_agg" : 0.000000,
        "bw_mean" : 0.000000,
        "bw_dev" : 0.000000,
        "bw_samples" : 0,
        "iops_min" : 0,
        "iops_max" : 0,
        "iops_mean" : 0.000000,
        "iops_stddev" : 0.000000,
        "iops_samples" : 0
      },
      "sync" : {
        "total_ios" : 0,
        "lat_ns" : {
          "min" : 0,
          "max" : 0,
          "mean" : 0.000000,
          "stddev" : 0.000000,
          "N" : 0
        }
      },
      "job_runtime" : 87914,
      "usr_cpu" : 2.543395,
      "sys_cpu" : 4.839957,
      "ctx" : 440813,
      "majf" : 0,
      "minf" : 0,
      "iodepth_level" : {
        "1" : 0.100000,
        "2" : 0.100000,
        "4" : 0.100000,
        "8" : 0.100000,
        "16" : 99.992371,
        "32" : 0.000000,
        ">=64" : 0.000000
      },
      "iodepth_submit" : {
        "0" : 0.000000,
        "4" : 100.000000,
        "8" : 0.000000,
        "16" : 0.000000,
        "32" : 0.000000,
        "64" : 0.000000,
        ">=64" : 0.000000
      },
      "iodepth_complete" : {
        "0" : 0.000000,
        "4" : 99.999491,
        "8" : 0.000000,
        "16" : 0.100000,
        "32" : 0.000000,
        "64" : 0.000000,
        ">=64" : 0.000000
      },
      "latency_ns" : {
        "2" : 0.000000,
        "4" : 0.000000,
        "10" : 0.000000,
        "20" : 0.000000,
        "50" : 0.000000,
        "100" : 0.000000,
        "250" : 0.000000,
        "500" : 0.000000,
        "750" : 0.000000,
        "1000" : 0.000000
      },
      "latency_us" : {
        "2" : 0.000000,
        "4" : 0.000000,
        "10" : 0.000000,
        "20" : 0.000000,
        "50" : 0.010000,
        "100" : 0.015386,
        "250" : 0.249608,
        "500" : 4.184977,
        "750" : 9.702428,
        "1000" : 11.389287
      },
      "latency_ms" : {
        "2" : 40.267436,
        "4" : 29.911804,
        "10" : 4.276403,
        "20" : 0.010000,
        "50" : 0.000000,
        "100" : 0.000000,
        "250" : 0.000000,
        "500" : 0.000000,
        "750" : 0.000000,
        "1000" : 0.000000,
        "2000" : 0.000000,
        ">=2000" : 0.000000
      },
      "latency_depth" : 16,
      "latency_target" : 0,
      "latency_percentile" : 100.000000,
      "latency_window" : 0
    }
  ],
  "disk_util" : [
    {
      "name" : "nvme3n1",
      "read_ios" : 86,
      "write_ios" : 782280,
      "read_merges" : 0,
      "write_merges" : 0,
      "read_ticks" : 0,
      "write_ticks" : 1387367,
      "in_queue" : 1387367,
      "util" : 99.563458
    }
  ]
}
