{
  "fio version" : "fio-3.28",
  "timestamp" : 1740560510,
  "timestamp_ms" : 1740560510325,
  "time" : "Wed Feb 26 18:01:50 2025",
  "global options" : {
    "bs" : "4k",
    "ioengine" : "psync",
    "size" : "12G",
    "numjobs" : "1",
    "iodepth" : "1",
    "group_reporting" : "1",
    "direct" : "1",
    "thread" : "1",
    "filename" : "/dev/nvme3n1"
  },
  "jobs" : [
    {
      "jobname" : "randwrite",
      "groupid" : 0,
      "error" : 0,
      "eta" : 0,
      "elapsed" : 48,
      "job options" : {
        "rw" : "randwrite"
      },
      "read" : {
        "io_bytes" : 0,
        "io_kbytes" : 0,
        "bw_bytes" : 0,
        "bw" : 0,
        "iops" : 0.000000,
        "runtime" : 0,
        "total_ios" : 0,
        "short_ios" : 0,
        "drop_ios" : 0,
        "slat_ns" : {
          "min" : 0,
          "max" : 0,
          "mean" : 0.000000,
          "stddev" : 0.000000,
          "N" : 0
        },
        "clat_ns" : {
          "min" : 0,
          "max" : 0,
          "mean" : 0.000000,
          "stddev" : 0.000000,
          "N" : 0
        },
        "lat_ns" : {
          "min" : 0,
          "max" : 0,
          "mean" : 0.000000,
          "stddev" : 0.000000,
          "N" : 0
        },
        "bw_min" : 0,
        "bw_max" : 0,
        "bw_agg" : 0.000000,
        "bw_mean" : 0.000000,
        "bw_dev" : 0.000000,
        "bw_samples" : 0,
        "iops_min" : 0,
        "iops_max" : 0,
        "iops_mean" : 0.000000,
        "iops_stddev" : 0.000000,
        "iops_samples" : 0
      },
      "write" : {
        "io_bytes" : 12884901888,
        "io_kbytes" : 12582912,
        "bw_bytes" : 271089877,
        "bw" : 264736,
        "iops" : 66184.052178,
        "runtime" : 47530,
        "total_ios" : 3145728,
        "short_ios" : 0,
        "drop_ios" : 0,
        "slat_ns" : {
          "min" : 0,
          "max" : 0,
          "mean" : 0.000000,
          "stddev" : 0.000000,
          "N" : 0
        },
        "clat_ns" : {
          "min" : 10060,
          "max" : 156159,
          "mean" : 14872.773917,
          "stddev" : 8171.556782,
          "N" : 3145728,
          "percentile" : {
            "1.000000" : 10688,
            "5.000000" : 10944,
            "10.000000" : 10944,
            "20.000000" : 11200,
            "30.000000" : 11328,
            "40.000000" : 11456,
            "50.000000" : 11584,
            "60.000000" : 11712,
            "70.000000" : 11968,
            "80.000000" : 16064,
            "90.000000" : 25472,
            "95.000000" : 33024,
            "99.000000" : 48384,
            "99.500000" : 55040,
            "99.900000" : 70144,
            "99.950000" : 76288,
            "99.990000" : 90624
          }
        },
        "lat_ns" : {
          "min" : 10100,
          "max" : 156199,
          "mean" : 14909.794217,
          "stddev" : 8171.322346,
          "N" : 3145728
        },
        "bw_min" : 261896,
        "bw_max" : 267672,
        "bw_agg" : 100.000000,
        "bw_mean" : 264768.421053,
        "bw_dev" : 1148.750955,
        "bw_samples" : 95,
        "iops_min" : 65474,
        "iops_max" : 66918,
        "iops_mean" : 66192.126316,
        "iops_stddev" : 287.187063,
        "iops_samples" : 95
      },
      "trim" : {
        "io_bytes" : 0,
        "io_kbytes" : 0,
        "bw_bytes" : 0,
        "bw" : 0,
        "iops" : 0.000000,
        "runtime" : 0,
        "total_ios" : 0,
        "short_ios" : 0,
        "drop_ios" : 0,
        "slat_ns" : {
          "min" : 0,
          "max" : 0,
          "mean" : 0.000000,
          "stddev" : 0.000000,
          "N" : 0
        },
        "clat_ns" : {
          "min" : 0,
          "max" : 0,
          "mean" : 0.000000,
          "stddev" : 0.000000,
          "N" : 0
        },
        "lat_ns" : {
          "min" : 0,
          "max" : 0,
          "mean" : 0.000000,
          "stddev" : 0.000000,
          "N" : 0
        },
        "bw_min" : 0,
        "bw_max" : 0,
        "bw_agg" : 0.000000,
        "bw_mean" : 0.000000,
        "bw_dev" : 0.000000,
        "bw_samples" : 0,
        "iops_min" : 0,
        "iops_max" : 0,
        "iops_mean" : 0.000000,
        "iops_stddev" : 0.000000,
        "iops_samples" : 0
      },
      "sync" : {
        "total_ios" : 0,
        "lat_ns" : {
          "min" : 0,
          "max" : 0,
          "mean" : 0.000000,
          "stddev" : 0.000000,
          "N" : 0
        }
      },
      "job_runtime" : 47529,
      "usr_cpu" : 2.398536,
      "sys_cpu" : 21.891898,
      "ctx" : 3145795,
      "majf" : 0,
      "minf" : 0,
      "iodepth_level" : {
        "1" : 100.000000,
        "2" : 0.000000,
        "4" : 0.000000,
        "8" : 0.000000,
        "16" : 0.000000,
        "32" : 0.000000,
        ">=64" : 0.000000
      },
      "iodepth_submit" : {
        "0" : 0.000000,
        "4" : 100.000000,
        "8" : 0.000000,
        "16" : 0.000000,
        "32" : 0.000000,
        "64" : 0.000000,
        ">=64" : 0.000000
      },
      "iodepth_complete" : {
        "0" : 0.000000,
        "4" : 100.000000,
        "8" : 0.000000,
        "16" : 0.000000,
        "32" : 0.000000,
        "64" : 0.000000,
        ">=64" : 0.000000
      },
      "latency_ns" : {
        "2" : 0.000000,
        "4" : 0.000000,
        "10" : 0.000000,
        "20" : 0.000000,
        "50" : 0.000000,
        "100" : 0.000000,
        "250" : 0.000000,
        "500" : 0.000000,
        "750" : 0.000000,
        "1000" : 0.000000
      },
      "latency_us" : {
        "2" : 0.000000,
        "4" : 0.000000,
        "10" : 0.000000,
        "20" : 85.069688,
        "50" : 14.055475,
        "100" : 0.871372,
        "250" : 0.010000,
        "500" : 0.000000,
        "750" : 0.000000,
        "1000" : 0.000000
      },
      "latency_ms" : {
        "2" : 0.000000,
        "4" : 0.000000,
        "10" : 0.000000,
        "20" : 0.000000,
        "50" : 0.000000,
        "100" : 0.000000,
        "250" : 0.000000,
        "500" : 0.000000,
        "750" : 0.000000,
        "1000" : 0.000000,
        "2000" : 0.000000,
        ">=2000" : 0.000000
      },
      "latency_depth" : 1,
      "latency_target" : 0,
      "latency_percentile" : 100.000000,
      "latency_window" : 0
    }
  ],
  "disk_util" : [
    {
      "name" : "nvme3n1",
      "read_ios" : 43,
      "write_ios" : 3135844,
      "read_merges" : 0,
      "write_merges" : 0,
      "read_ticks" : 0,
      "write_ticks" : 36965,
      "in_queue" : 36965,
      "util" : 83.706434
    }
  ]
}
