{
  "fio version" : "fio-3.28",
  "timestamp" : 1733764796,
  "timestamp_ms" : 1733764796189,
  "time" : "Tue Dec 10 02:19:56 2024",
  "global options" : {
    "bs" : "4k",
    "ioengine" : "psync",
    "filesize" : "4G",
    "numjobs" : "1",
    "iodepth" : "1",
    "group_reporting" : "1",
    "runtime" : "30",
    "direct" : "1",
    "thread" : "1",
    "time_based" : "1",
    "filename" : "/dev/nvme3n1"
  },
  "jobs" : [
    {
      "jobname" : "seqread",
      "groupid" : 0,
      "error" : 0,
      "eta" : 0,
      "elapsed" : 31,
      "job options" : {
        "rw" : "read"
      },
      "read" : {
        "io_bytes" : 1949556736,
        "io_kbytes" : 1903864,
        "bw_bytes" : 64983058,
        "bw" : 63460,
        "iops" : 15865.004500,
        "runtime" : 30001,
        "total_ios" : 475966,
        "short_ios" : 0,
        "drop_ios" : 0,
        "slat_ns" : {
          "min" : 0,
          "max" : 0,
          "mean" : 0.000000,
          "stddev" : 0.000000,
          "N" : 0
        },
        "clat_ns" : {
          "min" : 61849,
          "max" : 420983,
          "mean" : 62784.567543,
          "stddev" : 1289.554103,
          "N" : 475966,
          "percentile" : {
            "1.000000" : 62208,
            "5.000000" : 62208,
            "10.000000" : 62208,
            "20.000000" : 62208,
            "30.000000" : 62720,
            "40.000000" : 62720,
            "50.000000" : 62720,
            "60.000000" : 62720,
            "70.000000" : 62720,
            "80.000000" : 63232,
            "90.000000" : 63232,
            "95.000000" : 63744,
            "99.000000" : 64768,
            "99.500000" : 66048,
            "99.900000" : 70144,
            "99.950000" : 74240,
            "99.990000" : 111104
          }
        },
        "lat_ns" : {
          "min" : 61879,
          "max" : 421003,
          "mean" : 62809.858286,
          "stddev" : 1292.287630,
          "N" : 475966
        },
        "bw_min" : 63104,
        "bw_max" : 63704,
        "bw_agg" : 100.000000,
        "bw_mean" : 63480.542373,
        "bw_dev" : 132.821805,
        "bw_samples" : 59,
        "iops_min" : 15776,
        "iops_max" : 15926,
        "iops_mean" : 15870.135593,
        "iops_stddev" : 33.205451,
        "iops_samples" : 59
      },
      "write" : {
        "io_bytes" : 0,
        "io_kbytes" : 0,
        "bw_bytes" : 0,
        "bw" : 0,
        "iops" : 0.000000,
        "runtime" : 0,
        "total_ios" : 0,
        "short_ios" : 0,
        "drop_ios" : 0,
        "slat_ns" : {
          "min" : 0,
          "max" : 0,
          "mean" : 0.000000,
          "stddev" : 0.000000,
          "N" : 0
        },
        "clat_ns" : {
          "min" : 0,
          "max" : 0,
          "mean" : 0.000000,
          "stddev" : 0.000000,
          "N" : 0
        },
        "lat_ns" : {
          "min" : 0,
          "max" : 0,
          "mean" : 0.000000,
          "stddev" : 0.000000,
          "N" : 0
        },
        "bw_min" : 0,
        "bw_max" : 0,
        "bw_agg" : 0.000000,
        "bw_mean" : 0.000000,
        "bw_dev" : 0.000000,
        "bw_samples" : 0,
        "iops_min" : 0,
        "iops_max" : 0,
        "iops_mean" : 0.000000,
        "iops_stddev" : 0.000000,
        "iops_samples" : 0
      },
      "trim" : {
        "io_bytes" : 0,
        "io_kbytes" : 0,
        "bw_bytes" : 0,
        "bw" : 0,
        "iops" : 0.000000,
        "runtime" : 0,
        "total_ios" : 0,
        "short_ios" : 0,
        "drop_ios" : 0,
        "slat_ns" : {
          "min" : 0,
          "max" : 0,
          "mean" : 0.000000,
          "stddev" : 0.000000,
          "N" : 0
        },
        "clat_ns" : {
          "min" : 0,
          "max" : 0,
          "mean" : 0.000000,
          "stddev" : 0.000000,
          "N" : 0
        },
        "lat_ns" : {
          "min" : 0,
          "max" : 0,
          "mean" : 0.000000,
          "stddev" : 0.000000,
          "N" : 0
        },
        "bw_min" : 0,
        "bw_max" : 0,
        "bw_agg" : 0.000000,
        "bw_mean" : 0.000000,
        "bw_dev" : 0.000000,
        "bw_samples" : 0,
        "iops_min" : 0,
        "iops_max" : 0,
        "iops_mean" : 0.000000,
        "iops_stddev" : 0.000000,
        "iops_samples" : 0
      },
      "sync" : {
        "total_ios" : 0,
        "lat_ns" : {
          "min" : 0,
          "max" : 0,
          "mean" : 0.000000,
          "stddev" : 0.000000,
          "N" : 0
        }
      },
      "job_runtime" : 30000,
      "usr_cpu" : 0.660000,
      "sys_cpu" : 5.613333,
      "ctx" : 475969,
      "majf" : 0,
      "minf" : 1,
      "iodepth_level" : {
        "1" : 100.000000,
        "2" : 0.000000,
        "4" : 0.000000,
        "8" : 0.000000,
        "16" : 0.000000,
        "32" : 0.000000,
        ">=64" : 0.000000
      },
      "iodepth_submit" : {
        "0" : 0.000000,
        "4" : 100.000000,
        "8" : 0.000000,
        "16" : 0.000000,
        "32" : 0.000000,
        "64" : 0.000000,
        ">=64" : 0.000000
      },
      "iodepth_complete" : {
        "0" : 0.000000,
        "4" : 100.000000,
        "8" : 0.000000,
        "16" : 0.000000,
        "32" : 0.000000,
        "64" : 0.000000,
        ">=64" : 0.000000
      },
      "latency_ns" : {
        "2" : 0.000000,
        "4" : 0.000000,
        "10" : 0.000000,
        "20" : 0.000000,
        "50" : 0.000000,
        "100" : 0.000000,
        "250" : 0.000000,
        "500" : 0.000000,
        "750" : 0.000000,
        "1000" : 0.000000
      },
      "latency_us" : {
        "2" : 0.000000,
        "4" : 0.000000,
        "10" : 0.000000,
        "20" : 0.000000,
        "50" : 0.000000,
        "100" : 99.988445,
        "250" : 0.011135,
        "500" : 0.010000,
        "750" : 0.000000,
        "1000" : 0.000000
      },
      "latency_ms" : {
        "2" : 0.000000,
        "4" : 0.000000,
        "10" : 0.000000,
        "20" : 0.000000,
        "50" : 0.000000,
        "100" : 0.000000,
        "250" : 0.000000,
        "500" : 0.000000,
        "750" : 0.000000,
        "1000" : 0.000000,
        "2000" : 0.000000,
        ">=2000" : 0.000000
      },
      "latency_depth" : 1,
      "latency_target" : 0,
      "latency_percentile" : 100.000000,
      "latency_window" : 0
    }
  ],
  "disk_util" : [
    {
      "name" : "nvme3n1",
      "read_ios" : 474326,
      "write_ios" : 0,
      "read_merges" : 0,
      "write_merges" : 0,
      "read_ticks" : 28191,
      "write_ticks" : 0,
      "in_queue" : 28191,
      "util" : 95.118210
    }
  ]
}
