{
  "fio version" : "fio-3.28",
  "timestamp" : 1743407815,
  "timestamp_ms" : 1743407815269,
  "time" : "Mon Mar 31 16:56:55 2025",
  "global options" : {
    "bs" : "64k",
    "ioengine" : "io_uring",
    "size" : "12G",
    "numjobs" : "4",
    "iodepth" : "16",
    "group_reporting" : "1",
    "direct" : "1",
    "thread" : "1",
    "filename" : "/dev/nvme3n1"
  },
  "jobs" : [
    {
      "jobname" : "seqwrite",
      "groupid" : 0,
      "error" : 0,
      "eta" : 0,
      "elapsed" : 16,
      "job options" : {
        "rw" : "rw"
      },
      "read" : {
        "io_bytes" : 25764560896,
        "io_kbytes" : 25160704,
        "bw_bytes" : 1728121329,
        "bw" : 1687618,
        "iops" : 26369.038836,
        "runtime" : 14909,
        "total_ios" : 393136,
        "short_ios" : 0,
        "drop_ios" : 0,
        "slat_ns" : {
          "min" : 2730,
          "max" : 149450,
          "mean" : 3423.782543,
          "stddev" : 1038.925394,
          "N" : 393136
        },
        "clat_ns" : {
          "min" : 6090,
          "max" : 32615523,
          "mean" : 1913523.623690,
          "stddev" : 2723009.835317,
          "N" : 393136,
          "percentile" : {
            "1.000000" : 60672,
            "5.000000" : 183296,
            "10.000000" : 226304,
            "20.000000" : 366592,
            "30.000000" : 651264,
            "40.000000" : 954368,
            "50.000000" : 1302528,
            "60.000000" : 1728512,
            "70.000000" : 2244608,
            "80.000000" : 2867200,
            "90.000000" : 4046848,
            "95.000000" : 5013504,
            "99.000000" : 7110656,
            "99.500000" : 26345472,
            "99.900000" : 29753344,
            "99.950000" : 31326208,
            "99.990000" : 32112640
          }
        },
        "lat_ns" : {
          "min" : 10520,
          "max" : 32618653,
          "mean" : 1916995.380454,
          "stddev" : 2723176.704557,
          "N" : 393136
        },
        "bw_min" : 505728,
        "bw_max" : 3799808,
        "bw_agg" : 100.000000,
        "bw_mean" : 2025183.043678,
        "bw_dev" : 298309.710074,
        "bw_samples" : 102,
        "iops_min" : 7902,
        "iops_max" : 59372,
        "iops_mean" : 31643.485057,
        "iops_stddev" : 4661.089220,
        "iops_samples" : 102
      },
      "write" : {
        "io_bytes" : 25775046656,
        "io_kbytes" : 25170944,
        "bw_bytes" : 1728824646,
        "bw" : 1688305,
        "iops" : 26379.770608,
        "runtime" : 14909,
        "total_ios" : 393296,
        "short_ios" : 0,
        "drop_ios" : 0,
        "slat_ns" : {
          "min" : 2480,
          "max" : 204771,
          "mean" : 3525.780913,
          "stddev" : 1288.388908,
          "N" : 393296
        },
        "clat_ns" : {
          "min" : 10420,
          "max" : 2205363,
          "mean" : 210884.768373,
          "stddev" : 118901.629039,
          "N" : 393296,
          "percentile" : {
            "1.000000" : 37120,
            "5.000000" : 48896,
            "10.000000" : 67072,
            "20.000000" : 99840,
            "30.000000" : 134144,
            "40.000000" : 166912,
            "50.000000" : 199680,
            "60.000000" : 228352,
            "70.000000" : 259072,
            "80.000000" : 305152,
            "90.000000" : 370688,
            "95.000000" : 428032,
            "99.000000" : 552960,
            "99.500000" : 602112,
            "99.900000" : 716800,
            "99.950000" : 765952,
            "99.990000" : 962560
          }
        },
        "lat_ns" : {
          "min" : 37120,
          "max" : 2208393,
          "mean" : 214458.990247,
          "stddev" : 118888.533556,
          "N" : 393296
        },
        "bw_min" : 503296,
        "bw_max" : 3809536,
        "bw_agg" : 100.000000,
        "bw_mean" : 2024719.595402,
        "bw_dev" : 297422.692438,
        "bw_samples" : 102,
        "iops_min" : 7864,
        "iops_max" : 59524,
        "iops_mean" : 31636.243678,
        "iops_stddev" : 4647.229569,
        "iops_samples" : 102
      },
      "trim" : {
        "io_bytes" : 0,
        "io_kbytes" : 0,
        "bw_bytes" : 0,
        "bw" : 0,
        "iops" : 0.000000,
        "runtime" : 0,
        "total_ios" : 0,
        "short_ios" : 0,
        "drop_ios" : 0,
        "slat_ns" : {
          "min" : 0,
          "max" : 0,
          "mean" : 0.000000,
          "stddev" : 0.000000,
          "N" : 0
        },
        "clat_ns" : {
          "min" : 0,
          "max" : 0,
          "mean" : 0.000000,
          "stddev" : 0.000000,
          "N" : 0
        },
        "lat_ns" : {
          "min" : 0,
          "max" : 0,
          "mean" : 0.000000,
          "stddev" : 0.000000,
          "N" : 0
        },
        "bw_min" : 0,
        "bw_max" : 0,
        "bw_agg" : 0.000000,
        "bw_mean" : 0.000000,
        "bw_dev" : 0.000000,
        "bw_samples" : 0,
        "iops_min" : 0,
        "iops_max" : 0,
        "iops_mean" : 0.000000,
        "iops_stddev" : 0.000000,
        "iops_samples" : 0
      },
      "sync" : {
        "total_ios" : 0,
        "lat_ns" : {
          "min" : 0,
          "max" : 0,
          "mean" : 0.000000,
          "stddev" : 0.000000,
          "N" : 0
        }
      },
      "job_runtime" : 52386,
      "usr_cpu" : 1.735196,
      "sys_cpu" : 8.284656,
      "ctx" : 654517,
      "majf" : 0,
      "minf" : 0,
      "iodepth_level" : {
        "1" : 0.100000,
        "2" : 0.100000,
        "4" : 0.100000,
        "8" : 0.100000,
        "16" : 99.992371,
        "32" : 0.000000,
        ">=64" : 0.000000
      },
      "iodepth_submit" : {
        "0" : 0.000000,
        "4" : 100.000000,
        "8" : 0.000000,
        "16" : 0.000000,
        "32" : 0.000000,
        "64" : 0.000000,
        ">=64" : 0.000000
      },
      "iodepth_complete" : {
        "0" : 0.000000,
        "4" : 99.999491,
        "8" : 0.000000,
        "16" : 0.100000,
        "32" : 0.000000,
        "64" : 0.000000,
        ">=64" : 0.000000
      },
      "latency_ns" : {
        "2" : 0.000000,
        "4" : 0.000000,
        "10" : 0.000000,
        "20" : 0.000000,
        "50" : 0.000000,
        "100" : 0.000000,
        "250" : 0.000000,
        "500" : 0.000000,
        "750" : 0.000000,
        "1000" : 0.000000
      },
      "latency_us" : {
        "2" : 0.000000,
        "4" : 0.000000,
        "10" : 0.010000,
        "20" : 0.106176,
        "50" : 2.940750,
        "100" : 7.702382,
        "250" : 29.256948,
        "500" : 21.365738,
        "750" : 5.326335,
        "1000" : 4.077148
      },
      "latency_ms" : {
        "2" : 11.991374,
        "4" : 12.068812,
        "10" : 4.749044,
        "20" : 0.013606,
        "50" : 0.392024,
        "100" : 0.000000,
        "250" : 0.000000,
        "500" : 0.000000,
        "750" : 0.000000,
        "1000" : 0.000000,
        "2000" : 0.000000,
        ">=2000" : 0.000000
      },
      "latency_depth" : 16,
      "latency_target" : 0,
      "latency_percentile" : 100.000000,
      "latency_window" : 0
    }
  ],
  "disk_util" : [
    {
      "name" : "nvme3n1",
      "read_ios" : 393026,
      "write_ios" : 393038,
      "read_merges" : 0,
      "write_merges" : 0,
      "read_ticks" : 750125,
      "write_ticks" : 80941,
      "in_queue" : 831067,
      "util" : 99.366286
    }
  ]
}
